openlineage_sql/__init__.py
openlineage_sql/__init__.pyi
openlineage_sql/openlineage_sql.abi3.so
openlineage_sql/py.typed
openlineage_sql-1.42.1.dist-info/METADATA
openlineage_sql-1.42.1.dist-info/WHEEL
openlineage_sql-1.42.1.dist-info/RECORD
