Metadata-Version: 2.4
Name: openlineage_sql
Version: 1.42.1
Classifier: Programming Language :: Rust
Classifier: Programming Language :: Python :: 3.9
Classifier: Programming Language :: Python :: 3.10
Classifier: Programming Language :: Python :: 3.11
Classifier: Programming Language :: Python :: 3.12
Classifier: Programming Language :: Python :: 3.13
Classifier: Programming Language :: Python :: Implementation :: CPython
Classifier: Programming Language :: Python :: Implementation :: PyPy
Summary: Python interface for the Rust OpenLineage lineage extraction library
Keywords: openlineage
Author: OpenLineage
Requires-Python: >=3.9
